snippet_fmt/__init__.py
snippet_fmt/__main__.py
snippet_fmt/config.py
snippet_fmt/formatters.py
snippet_fmt/py.typed
snippet_fmt-0.1.5.dist-info/LICENSE
snippet_fmt-0.1.5.dist-info/METADATA
snippet_fmt-0.1.5.dist-info/WHEEL
snippet_fmt-0.1.5.dist-info/entry_points.txt
snippet_fmt-0.1.5.dist-info/RECORD
