Metadata-Version: 2.1
Name: snippet-fmt
Version: 0.1.5
Summary: Format and validate code snippets in reStructuredText files.
Author-email: Dominic Davis-Foster <dominic@davis-foster.co.uk>
License: MIT
Keywords: docs,formatting,linting
Home-page: https://github.com/python-formate/snippet-fmt
Project-URL: Issue Tracker, https://github.com/python-formate/snippet-fmt/issues
Project-URL: Source Code, https://github.com/python-formate/snippet-fmt
Project-URL: Documentation, https://snippet-fmt.readthedocs.io/en/latest
Platform: Windows
Platform: macOS
Platform: Linux
Classifier: Development Status :: 4 - Beta
Classifier: Environment :: Console
Classifier: Intended Audience :: Developers
Classifier: License :: OSI Approved :: MIT License
Classifier: Operating System :: OS Independent
Classifier: Programming Language :: Python
Classifier: Programming Language :: Python :: 3 :: Only
Classifier: Programming Language :: Python :: 3.6
Classifier: Programming Language :: Python :: 3.7
Classifier: Programming Language :: Python :: 3.8
Classifier: Programming Language :: Python :: 3.9
Classifier: Programming Language :: Python :: 3.10
Classifier: Programming Language :: Python :: 3.11
Classifier: Programming Language :: Python :: 3.12
Classifier: Programming Language :: Python :: Implementation :: CPython
Classifier: Typing :: Typed
Requires-Python: >=3.6
Requires-Dist: click>=8.0.1
Requires-Dist: consolekit>=1.2.3
Requires-Dist: dom-toml>=0.5.0
Requires-Dist: domdf-python-tools>=3.0.0
Requires-Dist: entrypoints>=0.3
Requires-Dist: formate>=0.4.9
Requires-Dist: typing-extensions>=3.10.0.0
